LICENSE
README.md
setup.py
neat/__init__.py
neat/activations.py
neat/aggregations.py
neat/attributes.py
neat/checkpoint.py
neat/config.py
neat/distributed.py
neat/genes.py
neat/genome.py
neat/graphs.py
neat/math_util.py
neat/parallel.py
neat/population.py
neat/reporting.py
neat/reproduction.py
neat/species.py
neat/stagnation.py
neat/statistics.py
neat/threaded.py
neat/ctrnn/__init__.py
neat/iznn/__init__.py
neat/nn/__init__.py
neat/nn/feed_forward.py
neat/nn/recurrent.py
neat_python_2023.egg-info/PKG-INFO
neat_python_2023.egg-info/SOURCES.txt
neat_python_2023.egg-info/dependency_links.txt
neat_python_2023.egg-info/top_level.txt