Metadata-Version: 2.1
Name: neat-python-2023
Version: 0.93
Summary: A NEAT (NeuroEvolution of Augmenting Topologies) implementation
Home-page: https://github.com/CodeReclaimers/neat-python
Author: Alan Mcintyre, Cesar Gomes Miguel, Carolina Feher da Silva, Marcio Lobo Netto
Author-email: alan@codereclaimers.com
Maintainer: Alan McIntyre
Maintainer-email: alan@codereclaimers.com
License: BSD
Classifier: Development Status :: 4 - Beta
Classifier: Intended Audience :: Developers
Classifier: Intended Audience :: Education
Classifier: Intended Audience :: Science/Research
Classifier: License :: OSI Approved :: BSD License
Classifier: Operating System :: OS Independent
Classifier: Programming Language :: Python :: 3.6
Classifier: Programming Language :: Python :: 3.7
Classifier: Programming Language :: Python :: 3.8
Classifier: Programming Language :: Python :: 3.9
Classifier: Programming Language :: Python :: 3.10
Classifier: Programming Language :: Python :: 3.11
Classifier: Programming Language :: Python :: Implementation :: PyPy
Classifier: Topic :: Scientific/Engineering
License-File: LICENSE
